tlslib.py
tlslib-0.dist-info/WHEEL
tlslib-0.dist-info/METADATA
tlslib-0.dist-info/RECORD
