Metadata-Version: 2.1
Name: tlslib
Version: 0
Summary: Reserving the name 'tlslib'
Author-email: Seth Michael Larson <sethmichaellarson@gmail.com>
